turkishpythonV2/__init__.py
turkishpythonV2/core.py
turkishpythonv2-2.0.0.dist-info/METADATA
turkishpythonv2-2.0.0.dist-info/WHEEL
turkishpythonv2-2.0.0.dist-info/top_level.txt
turkishpythonv2-2.0.0.dist-info/RECORD
