Metadata-Version: 2.4
Name: turkishpythonV2
Version: 2.0.0
Summary: Tam Türkçe Python (V2)
License: MIT
Requires-Python: >=3.7
Dynamic: license
Dynamic: requires-python
Dynamic: summary
